designmc/__init__.py
designmc/cli.py
designmc/designmc.py
designmc-0.1.0.dist-info/LICENSE
designmc-0.1.0.dist-info/METADATA
designmc-0.1.0.dist-info/WHEEL
designmc-0.1.0.dist-info/entry_points.txt
designmc-0.1.0.dist-info/top_level.txt
designmc-0.1.0.dist-info/RECORD
